Metadata-Version: 1.0
Name: GBI-distributions
Version: 0.2
Summary: Gaussian distributions
Home-page: UNKNOWN
Author: Parinaz Farajiparvar
Author-email: UNKNOWN
License: UNKNOWN
Platform: UNKNOWN
